LICENSE
MANIFEST.in
README.md
pyproject.toml
setup.cfg
setup.py
versioneer.py
merlin/systems/__init__.py
merlin/systems/_version.py
merlin/systems/model_registry.py
merlin/systems/dag/__init__.py
merlin/systems/dag/ensemble.py
merlin/systems/dag/ops/__init__.py
merlin/systems/dag/ops/compat.py
merlin/systems/dag/ops/faiss.py
merlin/systems/dag/ops/feast.py
merlin/systems/dag/ops/fil.py
merlin/systems/dag/ops/implicit.py
merlin/systems/dag/ops/pytorch.py
merlin/systems/dag/ops/session_filter.py
merlin/systems/dag/ops/softmax_sampling.py
merlin/systems/dag/ops/tensorflow.py
merlin/systems/dag/ops/unroll_features.py
merlin/systems/dag/ops/workflow.py
merlin/systems/dag/runtimes/__init__.py
merlin/systems/dag/runtimes/triton/__init__.py
merlin/systems/dag/runtimes/triton/runtime.py
merlin/systems/dag/runtimes/triton/ops/__init__.py
merlin/systems/dag/runtimes/triton/ops/fil.py
merlin/systems/dag/runtimes/triton/ops/operator.py
merlin/systems/dag/runtimes/triton/ops/pytorch.py
merlin/systems/dag/runtimes/triton/ops/tensorflow.py
merlin/systems/dag/runtimes/triton/ops/workflow.py
merlin/systems/triton/__init__.py
merlin/systems/triton/conversions.py
merlin/systems/triton/export.py
merlin/systems/triton/utils.py
merlin/systems/triton/models/__init__.py
merlin/systems/triton/models/executor_model.py
merlin/systems/triton/models/pytorch_model.py
merlin/systems/triton/models/workflow_model.py
merlin/systems/workflow/__init__.py
merlin/systems/workflow/base.py
merlin_systems.egg-info/PKG-INFO
merlin_systems.egg-info/SOURCES.txt
merlin_systems.egg-info/dependency_links.txt
merlin_systems.egg-info/not-zip-safe
merlin_systems.egg-info/requires.txt
merlin_systems.egg-info/top_level.txt
requirements/base.txt
requirements/dev.txt
requirements/docs.txt
requirements/gpu.txt
requirements/test-cpu.txt
requirements/test-gpu.txt
requirements/test.txt