Metadata-Version: 2.1
Name: merlin-systems
Version: 23.8.0
Summary: UNKNOWN
Home-page: https://github.com/NVIDIA-Merlin/systems
Author: NVIDIA Corporation
License: Apache 2.0
Platform: UNKNOWN
Classifier: Development Status :: 4 - Beta
Classifier: Programming Language :: Python :: 3
Classifier: Programming Language :: Python :: 3.8
Classifier: Programming Language :: Python :: 3.9
Classifier: Programming Language :: Python :: 3.10
Classifier: Programming Language :: Python :: 3 :: Only
Classifier: Intended Audience :: Developers
Classifier: License :: OSI Approved :: Apache Software License
Classifier: Topic :: Software Development :: Libraries
Classifier: Topic :: Scientific/Engineering
Requires-Python: >=3.8
Provides-Extra: cpu
Provides-Extra: gpu
Provides-Extra: dev
Provides-Extra: test
Provides-Extra: test-cpu
Provides-Extra: test-gpu
Provides-Extra: docs
License-File: LICENSE
